njsd
