Metadata-Version: 2.1
Name: njsd
Version: 0.1.4
Summary: Calculate Jensen-Shannon Divergence between two gene expression profiles to measure transcriptome-based intratumor heterogeneity(tITH).
Home-page: https://github.com/iron-lion/nJSD
Author: Youngjune Park
Author-email: regjah@gmail.com
Maintainer: Dohoon Lee
Maintainer-email: dohlee.bioinfo@gmail.com
License: BSD 2-Clause License
Platform: UNKNOWN
Classifier: Development Status :: 5 - Production/Stable
Classifier: Intended Audience :: Developers
Classifier: License :: OSI Approved :: BSD License
Classifier: Operating System :: Unix
Classifier: Operating System :: POSIX
Classifier: Operating System :: Microsoft :: Windows
Classifier: Programming Language :: Python
Classifier: Programming Language :: Python :: 3
Classifier: Programming Language :: Python :: 3.4
Classifier: Programming Language :: Python :: 3.5
Classifier: Programming Language :: Python :: 3.6
Classifier: Topic :: Utilities
Classifier: Topic :: Scientific/Engineering :: Bio-Informatics
